Metadata-Version: 2.1
Name: y-class-files
Version: 0.3
Summary: Class for working with files
Author-email: nospex28@gmail.com
